polywrap_client_config_builder/__init__.py
polywrap_client_config_builder/configures/__init__.py
polywrap_client_config_builder/configures/base_configure.py
polywrap_client_config_builder/configures/env_configure.py
polywrap_client_config_builder/configures/interface_configure.py
polywrap_client_config_builder/configures/package_configure.py
polywrap_client_config_builder/configures/redirect_configure.py
polywrap_client_config_builder/configures/resolver_configure.py
polywrap_client_config_builder/configures/wrapper_configure.py
polywrap_client_config_builder/polywrap_client_config_builder.py
polywrap_client_config_builder/py.typed
polywrap_client_config_builder/types/__init__.py
polywrap_client_config_builder/types/build_options.py
polywrap_client_config_builder/types/builder_config.py
polywrap_client_config_builder/types/bundle_package.py
polywrap_client_config_builder/types/client_config_builder.py
polywrap_client_config_builder-0.1.2.dist-info/METADATA
polywrap_client_config_builder-0.1.2.dist-info/WHEEL
polywrap_client_config_builder-0.1.2.dist-info/RECORD
