Metadata-Version: 2.1
Name: polywrap-client-config-builder
Version: 0.1.2
Summary: PolywrapClientConfigBuilder - A utility class for building the PolywrapClient config.
Author: Media
Author-email: media@polywrap.io
Requires-Python: >=3.10,<4.0
Classifier: Programming Language :: Python :: 3
Classifier: Programming Language :: Python :: 3.10
Classifier: Programming Language :: Python :: 3.11
Requires-Dist: polywrap-core (==0.1.2)
Requires-Dist: polywrap-uri-resolvers (==0.1.2)
